[
  {
    "Name": "Coin"
  },
  {
    "Name": "Test"
  },
  {
    "Name": "Service"
  },
  {
    "Name": "Start/Enter"
  },
  {
    "Name": "MarioBtn"
  },
  {
    "Name": "Item"
  },
  {
    "Name": "BananaCard"
  },
  {
    "Name": ""
  },
  {
    "Name": "MenuDown"
  },
  {
    "Name": "MenuUp"
  },
  {
    "Name": ""
  },
  {
    "Name": ""
  },
  {
    "Name": ""
  },
  {
    "Name": ""
  },
  {
    "Name": ""
  },
  {
    "Name": ""
  },
  {
    "Name": ""
  },
  {
    "Name": ""
  },
  {
    "Name": ""
  },
  {
    "Name": ""
  },
  {
    "Name": ""
  },
  {
    "Name": ""
  },
  {
    "Name": ""
  },
  {
    "Name": ""
  },
  {
    "Name": ""
  },
  {
    "Name": ""
  },
  {
    "Name": ""
  },
  {
    "Name": ""
  },
  {
    "Name": ""
  },
  {
    "Name": ""
  },
  {
    "Name": ""
  },
  {
    "Name": ""
  }
]